bg2vec/__init__.py
bg2vec/arguments.py
bg2vec/data_util.py
bg2vec/metrics.py
bg2vec/model.py
bg2vec/preprocessing.py
bg2vec/training.py
bg2vec-0.0.4.dist-info/METADATA
bg2vec-0.0.4.dist-info/WHEEL
bg2vec-0.0.4.dist-info/top_level.txt
bg2vec-0.0.4.dist-info/RECORD
